{
    "name": "FFMpeg\\Format\\ProgressListener\\AbstractProgressListener",
    "line": 22,
    "short_desc": "",
    "long_desc": "",
    "hint": null,
    "tags": {
        "author": [
            [
                "Robert",
                "Gruendler",
                "<r.gruendler@gmail.com>"
            ]
        ]
    },
    "namespace": "FFMpeg\\Format\\ProgressListener",
    "file": "src\/FFMpeg\/Format\/ProgressListener\/AbstractProgressListener.php",
    "hash": "a1021deb3bd7099b0f0cb55fc9a32c30f6878ab0",
    "parent": "Evenement\\EventEmitter",
    "modifiers": 16,
    "is_trait": false,
    "is_interface": false,
    "aliases": {
        "ListenerInterface": "Alchemy\\BinaryDriver\\Listeners\\ListenerInterface",
        "EventEmitter": "Evenement\\EventEmitter",
        "FFProbe": "FFMpeg\\FFProbe",
        "RuntimeException": "FFMpeg\\Exception\\RuntimeException"
    },
    "errors": [],
    "interfaces": {
        "Alchemy\\BinaryDriver\\Listeners\\ListenerInterface": "Alchemy\\BinaryDriver\\Listeners\\ListenerInterface"
    },
    "properties": [],
    "methods": {
        "__construct": {
            "name": "__construct",
            "line": 83,
            "short_desc": "",
            "long_desc": "",
            "hint": null,
            "hint_desc": null,
            "tags": [],
            "modifiers": "1",
            "is_by_ref": "",
            "exceptions": [
                [
                    "RuntimeException",
                    ""
                ]
            ],
            "errors": [
                "\"5\" @param tags are expected but only \"4\" found"
            ],
            "parameters": {
                "ffprobe": {
                    "name": "ffprobe",
                    "line": 83,
                    "short_desc": null,
                    "long_desc": null,
                    "hint": [
                        [
                            "FFMpeg\\FFProbe",
                            false
                        ]
                    ],
                    "tags": [],
                    "modifiers": "FFProbe",
                    "default": null,
                    "is_by_ref": false
                },
                "pathfile": {
                    "name": "pathfile",
                    "line": 83,
                    "short_desc": null,
                    "long_desc": null,
                    "hint": null,
                    "tags": [],
                    "modifiers": "",
                    "default": null,
                    "is_by_ref": false
                },
                "currentPass": {
                    "name": "currentPass",
                    "line": 83,
                    "short_desc": null,
                    "long_desc": null,
                    "hint": null,
                    "tags": [],
                    "modifiers": "",
                    "default": null,
                    "is_by_ref": false
                },
                "totalPass": {
                    "name": "totalPass",
                    "line": 83,
                    "short_desc": null,
                    "long_desc": null,
                    "hint": null,
                    "tags": [],
                    "modifiers": "",
                    "default": null,
                    "is_by_ref": false
                },
                "duration": {
                    "name": "duration",
                    "line": 83,
                    "short_desc": null,
                    "long_desc": null,
                    "hint": null,
                    "tags": [],
                    "modifiers": "",
                    "default": "0",
                    "is_by_ref": false
                }
            }
        },
        "getFFProbe": {
            "name": "getFFProbe",
            "line": 95,
            "short_desc": "",
            "long_desc": "",
            "hint": [
                [
                    "FFMpeg\\FFProbe",
                    false
                ]
            ],
            "hint_desc": "",
            "tags": [],
            "modifiers": "1",
            "is_by_ref": "",
            "exceptions": [],
            "errors": [],
            "parameters": []
        },
        "getPathfile": {
            "name": "getPathfile",
            "line": 103,
            "short_desc": "",
            "long_desc": "",
            "hint": [
                [
                    "string",
                    false
                ]
            ],
            "hint_desc": "",
            "tags": [],
            "modifiers": "1",
            "is_by_ref": "",
            "exceptions": [],
            "errors": [],
            "parameters": []
        },
        "getCurrentPass": {
            "name": "getCurrentPass",
            "line": 111,
            "short_desc": "",
            "long_desc": "",
            "hint": [
                [
                    "integer",
                    false
                ]
            ],
            "hint_desc": "",
            "tags": [],
            "modifiers": "1",
            "is_by_ref": "",
            "exceptions": [],
            "errors": [],
            "parameters": []
        },
        "getTotalPass": {
            "name": "getTotalPass",
            "line": 119,
            "short_desc": "",
            "long_desc": "",
            "hint": [
                [
                    "integer",
                    false
                ]
            ],
            "hint_desc": "",
            "tags": [],
            "modifiers": "1",
            "is_by_ref": "",
            "exceptions": [],
            "errors": [],
            "parameters": []
        },
        "getCurrentTime": {
            "name": "getCurrentTime",
            "line": 127,
            "short_desc": "",
            "long_desc": "",
            "hint": [
                [
                    "int",
                    false
                ]
            ],
            "hint_desc": "",
            "tags": [],
            "modifiers": "1",
            "is_by_ref": "",
            "exceptions": [],
            "errors": [],
            "parameters": []
        },
        "handle": {
            "name": "handle",
            "line": 135,
            "short_desc": "{@inheritdoc}",
            "long_desc": "",
            "hint": null,
            "hint_desc": null,
            "tags": [],
            "modifiers": "1",
            "is_by_ref": "",
            "exceptions": [],
            "errors": [],
            "parameters": {
                "type": {
                    "name": "type",
                    "line": 135,
                    "short_desc": null,
                    "long_desc": null,
                    "hint": null,
                    "tags": [],
                    "modifiers": "",
                    "default": null,
                    "is_by_ref": false
                },
                "data": {
                    "name": "data",
                    "line": 135,
                    "short_desc": null,
                    "long_desc": null,
                    "hint": null,
                    "tags": [],
                    "modifiers": "",
                    "default": null,
                    "is_by_ref": false
                }
            }
        },
        "forwardedEvents": {
            "name": "forwardedEvents",
            "line": 145,
            "short_desc": "{@inheritdoc}",
            "long_desc": "",
            "hint": null,
            "hint_desc": null,
            "tags": [],
            "modifiers": "1",
            "is_by_ref": "",
            "exceptions": [],
            "errors": [],
            "parameters": []
        }
    },
    "constants": []
}